<?xml version="1.0" encoding="UTF-8"?>
<!DOCTYPE dataset SYSTEM "data.dtd">
<!--  Auto-generated by the Maven Impex Plugin -->
<dataset>
    <KREW_DOC_TYP_T ACTV_IND="1" BLNKT_APPR_GRP_ID="1" CUR_IND="0"
        DOC_HDLR_URL="${kr.url}/maintenance.do?methodToCall=docHandler"
        DOC_TYP_DESC="Workflow Maintenance Document Type Document"
        DOC_TYP_ID="2011" DOC_TYP_NM="DocumentTypeDocument"
        DOC_TYP_VER_NBR="0" GRP_ID="1"
        HELP_DEF_URL="default.htm?turl=WordDocuments%2Fdocumenttype.htm"
        LBL="Workflow Maintenance Document Type Document"
        OBJ_ID="6166CBA1BA5D644DE0404F8189D86C09" PARNT_ID="2681"
        POST_PRCSR="org.kuali.rice.krad.workflow.postprocessor.KualiPostProcessor"
        RTE_VER_NBR="2" VER_NBR="1"/>
    <KREW_DOC_TYP_T ACTV_IND="1" BLNKT_APPR_GRP_ID="1" CUR_IND="1"
        DOC_HDLR_URL="${kr.url}/maintenance.do?methodToCall=docHandler"
        DOC_TYP_DESC="Rule Maintenance Document Type Document"
        DOC_TYP_ID="2012" DOC_TYP_NM="RoutingRuleDocument"
        DOC_TYP_VER_NBR="0" GRP_ID="1"
        LBL="Rule Maintenance Document Type Document"
        OBJ_ID="6166CBA1BA5E644DE0404F8189D86C09" PARNT_ID="2681"
        POST_PRCSR="org.kuali.rice.krad.workflow.postprocessor.KualiPostProcessor"
        RTE_VER_NBR="2" VER_NBR="0"/>
    <KREW_DOC_TYP_T ACTV_IND="1" BLNKT_APPR_GRP_ID="1" CUR_IND="1"
        DOC_HDLR_URL="${ken.url}/DetailView.form"
        DOC_TYP_DESC="This is the re-usable notification document type that will be used for delivering all notifications with KEW."
        DOC_TYP_ID="2023" DOC_TYP_NM="KualiNotification"
        DOC_TYP_VER_NBR="0" GRP_ID="2000" LBL="Notification"
        OBJ_ID="6166CBA1BA69644DE0404F8189D86C09"
        POST_PRCSR="org.kuali.rice.ken.postprocessor.kew.NotificationPostProcessor"
        RTE_VER_NBR="1" VER_NBR="0"/>
    <KREW_DOC_TYP_T ACTV_IND="1" BLNKT_APPR_GRP_ID="1" CUR_IND="1"
        DOC_HDLR_URL="${ken.url}/AdministerNotificationRequest.form"
        DOC_TYP_DESC="Create a New Notification Request"
        DOC_TYP_ID="2024" DOC_TYP_NM="SendNotificationRequest"
        DOC_TYP_VER_NBR="0" GRP_ID="1" LBL="Send Notification Request"
        OBJ_ID="6166CBA1BA6A644DE0404F8189D86C09"
        POST_PRCSR="org.kuali.rice.ken.postprocessor.kew.NotificationSenderFormPostProcessor"
        RTE_VER_NBR="2" VER_NBR="0"/>
    <KREW_DOC_TYP_T ACTV_IND="1" BLNKT_APPR_GRP_ID="1" CUR_IND="0"
        DOC_HDLR_URL="${kr.url}/maintenance.do?methodToCall=docHandler"
        DOC_TYP_DESC="Create a New Travel Account Maintenance Document"
        DOC_TYP_ID="2029" DOC_TYP_NM="TravelAccountMaintenanceDocument"
        DOC_TYP_VER_NBR="0" GRP_ID="1"
        LBL="Travel Account Maintenance Document"
        OBJ_ID="6166CBA1BA6F644DE0404F8189D86C09" PARNT_ID="2681"
        POST_PRCSR="org.kuali.rice.krad.workflow.postprocessor.KualiPostProcessor"
        RTE_VER_NBR="2" VER_NBR="1"/>
    <KREW_DOC_TYP_T ACTV_IND="1" BLNKT_APPR_GRP_ID="1" CUR_IND="1"
        DOC_HDLR_URL="${kr.url}/maintenance.do?methodToCall=docHandler"
        DOC_TYP_DESC="Create a New Travel Fiscal Officer"
        DOC_TYP_ID="2030" DOC_TYP_NM="FiscalOfficerMaintenanceDocument"
        DOC_TYP_VER_NBR="0" GRP_ID="1" LBL="Travel Fiscal Officer"
        OBJ_ID="6166CBA1BA70644DE0404F8189D86C09" PARNT_ID="2681"
        POST_PRCSR="org.kuali.rice.krad.workflow.postprocessor.KualiPostProcessor"
        RTE_VER_NBR="2" VER_NBR="0"/>
    <KREW_DOC_TYP_T ACTV_IND="1" BLNKT_APPR_GRP_ID="1" CUR_IND="0"
        DOC_HDLR_URL="${kr.url}/maintenance.do?methodToCall=docHandler"
        DOC_TYP_DESC="Create/edit parameter namespaces"
        DOC_TYP_ID="2031" DOC_TYP_NM="NamespaceMaintenanceDocument"
        DOC_TYP_VER_NBR="0" GRP_ID="1"
        HELP_DEF_URL="default.htm?turl=WordDocuments%2Fnamespace.htm"
        LBL="Namespace" OBJ_ID="6166CBA1BA71644DE0404F8189D86C09"
        PARNT_ID="2681"
        POST_PRCSR="org.kuali.rice.krad.workflow.postprocessor.KualiPostProcessor"
        RTE_VER_NBR="2" VER_NBR="1"/>
    <KREW_DOC_TYP_T ACTV_IND="1" BLNKT_APPR_GRP_ID="1" CUR_IND="0"
        DOC_HDLR_URL="${kr.url}/maintenance.do?methodToCall=docHandler"
        DOC_TYP_DESC="Create/edit a parameter type" DOC_TYP_ID="2032"
        DOC_TYP_NM="ParameterTypeMaintenanceDocument"
        DOC_TYP_VER_NBR="0" GRP_ID="1"
        HELP_DEF_URL="default.htm?turl=WordDocuments%2Fparametertype.htm"
        LBL="Parameter Type Maintenance Document"
        OBJ_ID="6166CBA1BA72644DE0404F8189D86C09" PARNT_ID="2681"
        POST_PRCSR="org.kuali.rice.krad.workflow.postprocessor.KualiPostProcessor"
        RTE_VER_NBR="2" VER_NBR="1"/>
    <KREW_DOC_TYP_T ACTV_IND="1" BLNKT_APPR_GRP_ID="1" CUR_IND="0"
        DOC_HDLR_URL="${kr.url}/maintenance.do?methodToCall=docHandler"
        DOC_TYP_DESC="Create/edit a parameter detail type"
        DOC_TYP_ID="2033"
        DOC_TYP_NM="ParameterDetailTypeMaintenanceDocument"
        DOC_TYP_VER_NBR="0" GRP_ID="1"
        HELP_DEF_URL="default.htm?turl=WordDocuments%2Fparametercomponent.htm"
        LBL="Parameter Detail Type Maintenance Document"
        OBJ_ID="6166CBA1BA73644DE0404F8189D86C09" PARNT_ID="2681"
        POST_PRCSR="org.kuali.rice.krad.workflow.postprocessor.KualiPostProcessor"
        RTE_VER_NBR="2" VER_NBR="1"/>
    <KREW_DOC_TYP_T ACTV_IND="1" BLNKT_APPR_GRP_ID="1" CUR_IND="0"
        DOC_HDLR_URL="${kr.url}/maintenance.do?methodToCall=docHandler"
        DOC_TYP_DESC="Create/edit a parameter" DOC_TYP_ID="2034"
        DOC_TYP_NM="ParameterMaintenanceDocument" DOC_TYP_VER_NBR="0"
        GRP_ID="1"
        HELP_DEF_URL="default.htm?turl=WordDocuments%2Fparameter.htm"
        LBL="Parameter Maintenance Document"
        OBJ_ID="6166CBA1BA74644DE0404F8189D86C09" PARNT_ID="2681"
        POST_PRCSR="org.kuali.rice.krad.workflow.postprocessor.KualiPostProcessor"
        RTE_VER_NBR="2" VER_NBR="1"/>
    <KREW_DOC_TYP_T ACTV_IND="1" BLNKT_APPR_PLCY="NONE" CUR_IND="1"
        DOC_HDLR_URL="${workflow.url}/EDocLite"
        DOC_TYP_DESC="eDoc.Example1 Parent Doctype" DOC_TYP_ID="2217"
        DOC_TYP_NM="eDoc.Example1.ParentDoctype" DOC_TYP_VER_NBR="0"
        GRP_ID="2200" LBL="eDoc.Example1 Parent Document"
        OBJ_ID="6166CBA1BA7B644DE0404F8189D86C09"
        POST_PRCSR="org.kuali.rice.edl.framework.workflow.EDocLitePostProcessor"
        RTE_VER_NBR="2" VER_NBR="0"/>
    <KREW_DOC_TYP_T ACTV_IND="1" BLNKT_APPR_GRP_ID="1" CUR_IND="1"
        DOC_HDLR_URL="none" DOC_TYP_DESC="SampleThinClientDocument"
        DOC_TYP_ID="2282" DOC_TYP_NM="SampleThinClientDocument"
        DOC_TYP_VER_NBR="0" GRP_ID="1" LBL="SampleThinClientDocument"
        OBJ_ID="6166CBA1BA7D644DE0404F8189D86C09"
        POST_PRCSR="org.kuali.rice.kew.postprocessor.DefaultPostProcessor"
        RTE_VER_NBR="2" VER_NBR="0"/>
    <KREW_DOC_TYP_T ACTV_IND="1" BLNKT_APPR_PLCY="NONE" CUR_IND="1"
        DOC_HDLR_URL="${workflow.url}/EDocLite"
        DOC_TYP_DESC="eDoc.Example1 Request DocumentType"
        DOC_TYP_ID="2440" DOC_TYP_NM="eDoc.Example1Doctype"
        DOC_TYP_VER_NBR="0" GRP_ID="2200"
        LBL="eDoc.Example1 Request DocumentType"
        OBJ_ID="6166CBA1BA80644DE0404F8189D86C09" PARNT_ID="2217"
        POST_PRCSR="org.kuali.rice.edl.framework.workflow.EDocLitePostProcessor"
        RTE_VER_NBR="2" VER_NBR="0"/>
    <KREW_DOC_TYP_T ACTV_IND="1" CUR_IND="1"
        DOC_TYP_DESC="KualiDocument" DOC_TYP_ID="2680"
        DOC_TYP_NM="KualiDocument" DOC_TYP_VER_NBR="0"
        LBL="KualiDocument" OBJ_ID="6166CBA1BA81644DE0404F8189D86C09"
        POST_PRCSR="org.kuali.rice.krad.workflow.postprocessor.KualiPostProcessor"
        RTE_VER_NBR="2" VER_NBR="40"/>
    <KREW_DOC_TYP_T ACTV_IND="1" CUR_IND="1"
        DOC_TYP_DESC="Parent Document Type for all Rice Documents"
        DOC_TYP_ID="2681" DOC_TYP_NM="RiceDocument" DOC_TYP_VER_NBR="0"
        LBL="Rice Document" OBJ_ID="6166CBA1BA82644DE0404F8189D86C09"
        PARNT_ID="2680" RTE_VER_NBR="2" VER_NBR="81"/>
    <KREW_DOC_TYP_T ACTV_IND="1" BLNKT_APPR_GRP_ID="1" CUR_IND="1"
        DOC_HDLR_URL="${application.url}/travelDocument2.do?methodToCall=docHandler"
        DOC_TYP_DESC="Create a New Travel Request" DOC_TYP_ID="2683"
        DOC_TYP_NM="TravelRequest" DOC_TYP_VER_NBR="0" GRP_ID="1"
        LBL="Travel Request" OBJ_ID="6166CBA1BA84644DE0404F8189D86C09"
        PARNT_ID="2681"
        POST_PRCSR="org.kuali.rice.krad.workflow.postprocessor.KualiPostProcessor"
        RTE_VER_NBR="2" VER_NBR="0"/>
    <KREW_DOC_TYP_T ACTV_IND="1" CUR_IND="0"
        DOC_HDLR_URL="${application.url}/kim/identityManagementPersonDocument.do?methodToCall=docHandler"
        DOC_TYP_ID="2697" DOC_TYP_NM="IdentityManagementPersonDocument"
        DOC_TYP_VER_NBR="0" LBL="Person Document"
        OBJ_ID="6166CBA1BA85644DE0404F8189D86C09" PARNT_ID="2681"
        RTE_VER_NBR="2" VER_NBR="1"/>
    <KREW_DOC_TYP_T ACTV_IND="1" CUR_IND="1"
        DOC_HDLR_URL="${kr.url}/maintenance.do?methodToCall=docHandler"
        DOC_TYP_DESC="Routing Rule Delegation" DOC_TYP_ID="2699"
        DOC_TYP_NM="RoutingRuleDelegationMaintenanceDocument"
        DOC_TYP_VER_NBR="0" LBL="Routing Rule Delegation"
        OBJ_ID="A6DC8753-AF90-7A01-0EF7-E6D446529668" PARNT_ID="2681"
        POST_PRCSR="org.kuali.rice.krad.workflow.postprocessor.KualiPostProcessor"
        RTE_VER_NBR="2" VER_NBR="0"/>
    <KREW_DOC_TYP_T ACTV_IND="1" CUR_IND="0"
        DOC_HDLR_URL="${application.url}/kim/identityManagementGroupDocument.do?methodToCall=docHandler"
        DOC_TYP_ID="2702" DOC_TYP_NM="IdentityManagementGroupDocument"
        DOC_TYP_VER_NBR="0" LBL="Group"
        OBJ_ID="6BE7733A-643E-666C-CD18-E7439476C12E" PARNT_ID="2681"
        RTE_VER_NBR="2" VER_NBR="1"/>
    <KREW_DOC_TYP_T ACTV_IND="1" CUR_IND="0"
        DOC_HDLR_URL="${application.url}/kim/identityManagementRoleDocument.do?methodToCall=docHandler"
        DOC_TYP_ID="2703" DOC_TYP_NM="IdentityManagementRoleDocument"
        DOC_TYP_VER_NBR="0" LBL="Role"
        OBJ_ID="EAF58989-D602-4CB1-961D-E31E0383B2D6" PARNT_ID="2681"
        RTE_VER_NBR="2" VER_NBR="1"/>
    <KREW_DOC_TYP_T ACTV_IND="1" APPL_ID="RECIPE" BLNKT_APPR_GRP_ID="1"
        CUR_IND="1"
        DOC_HDLR_URL="${application.url}/kr/maintenance.do?methodToCall=docHandler"
        DOC_TYP_DESC="Parent Document for Recipe Maintenance Documents"
        DOC_TYP_ID="2704" DOC_TYP_NM="RecipeParentMaintenanceDocument"
        DOC_TYP_VER_NBR="0" GRP_ID="1"
        LBL="Recipe Maintenance Document Parent"
        OBJ_ID="327B8EEB-BC71-4701-A9E8-B4FC878FFCA6" PARNT_ID="2681"
        POST_PRCSR="org.kuali.rice.krad.workflow.postprocessor.KualiPostProcessor"
        RTE_VER_NBR="2" VER_NBR="0"/>
    <KREW_DOC_TYP_T ACTV_IND="1" APPL_ID="RECIPE" BLNKT_APPR_GRP_ID="1"
        CUR_IND="1"
        DOC_HDLR_URL="${application.url}/kr/maintenance.do?methodToCall=docHandler"
        DOC_TYP_DESC="Create or Update a Recipe Category"
        DOC_TYP_ID="2705" DOC_TYP_NM="RecipeCategoryMaintenanceDocument"
        DOC_TYP_VER_NBR="0" GRP_ID="1" LBL="Recipe Category Maintenance"
        OBJ_ID="E9CB1AAD-0015-16D5-9149-EC2A4AEDE932" PARNT_ID="2704"
        POST_PRCSR="org.kuali.rice.krad.workflow.postprocessor.KualiPostProcessor"
        RTE_VER_NBR="2" VER_NBR="0"/>
    <KREW_DOC_TYP_T ACTV_IND="1" APPL_ID="RECIPE" BLNKT_APPR_GRP_ID="1"
        CUR_IND="1"
        DOC_HDLR_URL="${application.url}/kr/maintenance.do?methodToCall=docHandler"
        DOC_TYP_DESC="Create or Update a Recipe Ingredient"
        DOC_TYP_ID="2706"
        DOC_TYP_NM="RecipeIngredientMaintenanceDocument"
        DOC_TYP_VER_NBR="0" GRP_ID="1"
        LBL="Recipe Ingredient Maintenance"
        OBJ_ID="41800805-9154-D43E-785F-3E76255F7F97" PARNT_ID="2704"
        POST_PRCSR="org.kuali.rice.krad.workflow.postprocessor.KualiPostProcessor"
        RTE_VER_NBR="2" VER_NBR="0"/>
    <KREW_DOC_TYP_T ACTV_IND="1" APPL_ID="RECIPE" BLNKT_APPR_GRP_ID="1"
        CUR_IND="1"
        DOC_HDLR_URL="${application.url}/kr/maintenance.do?methodToCall=docHandler"
        DOC_TYP_DESC="Create or Update a Recipe" DOC_TYP_ID="2707"
        DOC_TYP_NM="RecipeMaintenanceDocument" DOC_TYP_VER_NBR="0"
        GRP_ID="1" LBL="Recipe Maintenance"
        OBJ_ID="C1CED233-6389-D07B-8ADD-B8043E50B599" PARNT_ID="2704"
        POST_PRCSR="edu.sampleu.recipe.kew.RecipesPostProcessor"
        RTE_VER_NBR="2" VER_NBR="0"/>
    <KREW_DOC_TYP_T ACTV_IND="1" CUR_IND="0"
        DOC_HDLR_URL="${kr.url}/maintenance.do?methodToCall=docHandler"
        DOC_TYP_ID="2708" DOC_TYP_NM="CampusMaintenanceDocument"
        DOC_TYP_VER_NBR="0"
        HELP_DEF_URL="default.htm?turl=WordDocuments%2Fcampus.htm"
        LBL="CampusMaintenanceDocument"
        OBJ_ID="616D94CA-D08D-D036-E77D-4B53DB34CD95" PARNT_ID="2681"
        RTE_VER_NBR="2" VER_NBR="1"/>
    <KREW_DOC_TYP_T ACTV_IND="1" CUR_IND="0"
        DOC_HDLR_URL="${kr.url}/maintenance.do?methodToCall=docHandler"
        DOC_TYP_ID="2709" DOC_TYP_NM="CampusTypeMaintenanceDocument"
        DOC_TYP_VER_NBR="0"
        HELP_DEF_URL="default.htm?turl=WordDocuments%2Fcampustype.htm"
        LBL="CampusTypeMaintenanceDocument"
        OBJ_ID="DE0B8588-E459-C07A-87B8-6ACD693AE70C" PARNT_ID="2681"
        RTE_VER_NBR="2" VER_NBR="1"/>
    <KREW_DOC_TYP_T ACTV_IND="1" CUR_IND="0"
        DOC_HDLR_URL="${kr.url}/maintenance.do?methodToCall=docHandler"
        DOC_TYP_ID="2710" DOC_TYP_NM="CountryMaintenanceDocument"
        DOC_TYP_VER_NBR="0"
        HELP_DEF_URL="default.htm?turl=WordDocuments%2Fcountry.htm"
        LBL="CountryMaintenanceDocument"
        OBJ_ID="82EDB593-97BA-428E-C6E7-A7F3031CFAEB" PARNT_ID="2681"
        RTE_VER_NBR="2" VER_NBR="1"/>
    <KREW_DOC_TYP_T ACTV_IND="1" CUR_IND="0"
        DOC_HDLR_URL="${kr.url}/maintenance.do?methodToCall=docHandler"
        DOC_TYP_ID="2711" DOC_TYP_NM="CountyMaintenanceDocument"
        DOC_TYP_VER_NBR="0"
        HELP_DEF_URL="default.htm?turl=WordDocuments%2Fcounty.htm"
        LBL="CountyMaintenanceDocument"
        OBJ_ID="C972E260-5552-BB63-72E6-A514301B0326" PARNT_ID="2681"
        RTE_VER_NBR="2" VER_NBR="1"/>
    <KREW_DOC_TYP_T ACTV_IND="1" CUR_IND="0"
        DOC_HDLR_URL="${kr.url}/maintenance.do?methodToCall=docHandler"
        DOC_TYP_ID="2712" DOC_TYP_NM="PostalCodeMaintenanceDocument"
        DOC_TYP_VER_NBR="0"
        HELP_DEF_URL="default.htm?turl=WordDocuments%2Fpostalcode.htm"
        LBL="PostalCodeMaintenanceDocument"
        OBJ_ID="B79D1104-BC48-1597-AFBE-773EED31A110" PARNT_ID="2681"
        RTE_VER_NBR="2" VER_NBR="1"/>
    <KREW_DOC_TYP_T ACTV_IND="1" CUR_IND="0"
        DOC_HDLR_URL="${kr.url}/maintenance.do?methodToCall=docHandler"
        DOC_TYP_ID="2713" DOC_TYP_NM="StateMaintenanceDocument"
        DOC_TYP_VER_NBR="0"
        HELP_DEF_URL="default.htm?turl=WordDocuments%2Fstate.htm"
        LBL="StateMaintenanceDocument"
        OBJ_ID="EF2378F6-E770-D7BF-B7F1-C18881E3AFF0" PARNT_ID="2681"
        RTE_VER_NBR="2" VER_NBR="1"/>
    <KREW_DOC_TYP_T ACTV_IND="1" CUR_IND="1" DOC_TYP_ID="2994"
        DOC_TYP_NM="IdentityManagementDocument" DOC_TYP_VER_NBR="0"
        LBL="Identity Management Document"
        OBJ_ID="944596CD-A7FC-0DEE-EDE1-52A52BED85CC" PARNT_ID="2681"
        RTE_VER_NBR="2" VER_NBR="16"/>
    <KREW_DOC_TYP_T ACTV_IND="1" CUR_IND="0"
        DOC_HDLR_URL="${kim.url}/identityManagementRoleDocument.do?methodToCall=docHandler"
        DOC_TYP_ID="2995" DOC_TYP_NM="IdentityManagementRoleDocument"
        DOC_TYP_VER_NBR="1"
        HELP_DEF_URL="default.htm?turl=WordDocuments%2Frole.htm"
        LBL="Role" OBJ_ID="FEA8D9DD-0592-0525-B2BD-2F4BA811CF30"
        PARNT_ID="2994" PREV_DOC_TYP_VER_NBR="2703" RTE_VER_NBR="2" VER_NBR="2"/>
    <KREW_DOC_TYP_T ACTV_IND="1" CUR_IND="0"
        DOC_HDLR_URL="${kim.url}/identityManagementGroupDocument.do?methodToCall=docHandler"
        DOC_TYP_ID="2996" DOC_TYP_NM="IdentityManagementGroupDocument"
        DOC_TYP_VER_NBR="1"
        HELP_DEF_URL="default.htm?turl=WordDocuments%2Fgroup.htm"
        LBL="Group" OBJ_ID="D9636763-7749-8F3F-4570-21181E977AE3"
        PARNT_ID="2994" PREV_DOC_TYP_VER_NBR="2702" RTE_VER_NBR="2" VER_NBR="2"/>
    <KREW_DOC_TYP_T ACTV_IND="1" CUR_IND="0"
        DOC_HDLR_URL="${kim.url}/identityManagementPersonDocument.do?methodToCall=docHandler"
        DOC_TYP_ID="2997" DOC_TYP_NM="IdentityManagementPersonDocument"
        DOC_TYP_VER_NBR="1"
        HELP_DEF_URL="default.htm?turl=WordDocuments%2Fperson.htm"
        LBL="Person" OBJ_ID="14C95FE4-1497-82C6-CBBD-BF16AD81B845"
        PARNT_ID="2994" PREV_DOC_TYP_VER_NBR="2697" RTE_VER_NBR="2" VER_NBR="2"/>
    <KREW_DOC_TYP_T ACTV_IND="1" CUR_IND="0"
        DOC_HDLR_URL="${kr.url}/maintenance.do?methodToCall=docHandler"
        DOC_TYP_ID="2998"
        DOC_TYP_NM="IdentityManagementReviewResponsibilityMaintenanceDocument"
        DOC_TYP_VER_NBR="0"
        HELP_DEF_URL="default.htm?turl=WordDocuments%2Fresponsibility.htm"
        LBL="Review Responsibility"
        OBJ_ID="66413887-3C82-B12D-9563-0A893E8D1910" PARNT_ID="2994"
        RTE_VER_NBR="2" VER_NBR="2"/>
    <KREW_DOC_TYP_T ACTV_IND="1" CUR_IND="0"
        DOC_HDLR_URL="${kr.url}/maintenance.do?methodToCall=docHandler"
        DOC_TYP_ID="2999"
        DOC_TYP_NM="IdentityManagementGenericPermissionMaintenanceDocument"
        DOC_TYP_VER_NBR="0"
        HELP_DEF_URL="default.htm?turl=WordDocuments%2Fpermission.htm"
        LBL="Permission" OBJ_ID="A3AE4787-018E-1F17-6EB6-F2F0F366774F"
        PARNT_ID="2994" RTE_VER_NBR="2" VER_NBR="2"/>
    <KREW_DOC_TYP_T ACTV_IND="1" BLNKT_APPR_GRP_ID="1" CUR_IND="1"
        DOC_HDLR_URL="${kr.krad.url}/krmsAgendaEditor?methodToCall=docHandler"
        DOC_TYP_DESC="Create a KRMS Agenda" DOC_TYP_ID="3000"
        DOC_TYP_NM="AgendaEditorMaintenanceDocument" DOC_TYP_VER_NBR="0"
        GRP_ID="1" LBL="KRMS Agenda Editor Maintenance Document"
        OBJ_ID="ebd70731-4d33-4c0b-a958-2b9ca047ae07" PARNT_ID="2681"
        POST_PRCSR="org.kuali.rice.krad.workflow.postprocessor.KualiPostProcessor"
        RTE_VER_NBR="2" VER_NBR="1"/>
    <KREW_DOC_TYP_T ACTV_IND="1" BLNKT_APPR_GRP_ID="1" CUR_IND="1"
        DOC_HDLR_URL="${kr.krad.url}/maintenance?methodToCall=docHandler"
        DOC_TYP_DESC="Create a New Agenda" DOC_TYP_ID="3001"
        DOC_TYP_NM="AgendaMaintenanceDocument" DOC_TYP_VER_NBR="0"
        GRP_ID="1" LBL="Agenda Maintenance Document"
        OBJ_ID="3198b708-6e29-4b19-bf35-51473cf8a3d1" PARNT_ID="2681"
        POST_PRCSR="org.kuali.rice.krad.workflow.postprocessor.KualiPostProcessor"
        RTE_VER_NBR="2" VER_NBR="1"/>
    <KREW_DOC_TYP_T ACTV_IND="1" CUR_IND="1"
        DOC_HDLR_URL="${kr.krad.url}/peopleFlowMaintenance?methodToCall=docHandler"
        DOC_TYP_ID="3002" DOC_TYP_NM="PeopleFlowMaintenanceDocument"
        DOC_TYP_VER_NBR="0" LBL="PeopleFlowMaintenanceDocument"
        OBJ_ID="2c0a1333-f60b-47c4-a9b0-76f32f1ed97d" PARNT_ID="2681"
        RTE_VER_NBR="2" VER_NBR="1"/>
    <KREW_DOC_TYP_T ACTV_IND="1" BLNKT_APPR_GRP_ID="1" CUR_IND="1"
        DOC_HDLR_URL="${kr.krad.url}/maintenance?methodToCall=docHandler"
        DOC_TYP_DESC="Create a KRMS Context" DOC_TYP_ID="3003"
        DOC_TYP_NM="ContextMaintenanceDocument" DOC_TYP_VER_NBR="0"
        GRP_ID="1" LBL="KRMS Context Maintenance Document"
        OBJ_ID="87413487-8306-4130-b2df-a5d0e42243f9" PARNT_ID="2681"
        POST_PRCSR="org.kuali.rice.krad.workflow.postprocessor.KualiPostProcessor"
        RTE_VER_NBR="2" VER_NBR="1"/>
    <KREW_DOC_TYP_T ACTV_IND="1" BLNKT_APPR_GRP_ID="1" CUR_IND="1"
        DOC_HDLR_URL="${kr.krad.url}/maintenance?methodToCall=docHandler"
        DOC_TYP_DESC="Create a KRMS Term" DOC_TYP_ID="3004"
        DOC_TYP_NM="TermMaintenanceDocument" DOC_TYP_VER_NBR="0"
        GRP_ID="1" LBL="KRMS Term Maintenance Document"
        OBJ_ID="bc83f80b-85c4-40fd-998c-ef53fdd97e3f" PARNT_ID="2681"
        POST_PRCSR="org.kuali.rice.krad.workflow.postprocessor.KualiPostProcessor"
        RTE_VER_NBR="2" VER_NBR="1"/>
    <KREW_DOC_TYP_T ACTV_IND="1" BLNKT_APPR_GRP_ID="1" CUR_IND="1"
        DOC_HDLR_URL="${kr.krad.url}/maintenance?methodToCall=docHandler"
        DOC_TYP_DESC="Create a KRMS Term Specification"
        DOC_TYP_ID="3005"
        DOC_TYP_NM="TermSpecificationMaintenanceDocument"
        DOC_TYP_VER_NBR="0" GRP_ID="1"
        LBL="KRMS Term Specification Maintenance Document"
        OBJ_ID="57e7ee1d-e44a-4154-9ba4-ee562c434c98" PARNT_ID="2681"
        POST_PRCSR="org.kuali.rice.krad.workflow.postprocessor.KualiPostProcessor"
        RTE_VER_NBR="2" VER_NBR="1"/>
    <KREW_DOC_TYP_T ACTV_IND="1" BLNKT_APPR_GRP_ID="1" CUR_IND="0"
        DOC_HDLR_URL="${kr.krad.url}/maintenance?methodToCall=docHandler"
        DOC_TYP_DESC="Create a New Travel Account Maintenance Document"
        DOC_TYP_ID="3006" DOC_TYP_NM="TravelAccountMaintenanceDocument"
        DOC_TYP_VER_NBR="1" GRP_ID="1"
        LBL="Travel Account Maintenance Document"
        OBJ_ID="0b89a795-8079-460a-b456-39c5c477938b" PARNT_ID="2681"
        POST_PRCSR="org.kuali.rice.krad.workflow.postprocessor.KualiPostProcessor"
        PREV_DOC_TYP_VER_NBR="2029" RTE_VER_NBR="2" VER_NBR="2"/>
    <KREW_DOC_TYP_T ACTV_IND="1" BLNKT_APPR_GRP_ID="1" CUR_IND="0"
        DOC_HDLR_URL="${kr.url}/maintenance.do?methodToCall=docHandler"
        DOC_TYP_DESC="Create/edit a component" DOC_TYP_ID="3007"
        DOC_TYP_NM="ComponentMaintenanceDocument" DOC_TYP_VER_NBR="0"
        GRP_ID="1"
        HELP_DEF_URL="default.htm?turl=WordDocuments%2Fparametertype.htm"
        LBL="Component Maintenance Document"
        OBJ_ID="e9e0086b-30ce-4a9b-a2d6-564772076a1e" PARNT_ID="2681"
        POST_PRCSR="org.kuali.rice.krad.workflow.postprocessor.KualiPostProcessor"
        RTE_VER_NBR="2" VER_NBR="2"/>
    <KREW_DOC_TYP_T ACTV_IND="1" BLNKT_APPR_GRP_ID="1" CUR_IND="0"
        DOC_HDLR_URL="${application.url}/kr-krad/approval?methodToCall=docHandler"
        DOC_TYP_DESC="Create a New Travel Authorization Document"
        DOC_TYP_ID="3008" DOC_TYP_NM="TravelAuthorization"
        DOC_TYP_VER_NBR="0" GRP_ID="1"
        LBL="Travel Authorization Document"
        OBJ_ID="b9110d38-8fe0-4123-a65a-5df2336795fa" PARNT_ID="2681"
        POST_PRCSR="org.kuali.rice.krad.workflow.postprocessor.KualiPostProcessor"
        RTE_VER_NBR="1" VER_NBR="2"/>
    <KREW_DOC_TYP_T ACTV_IND="1" BLNKT_APPR_GRP_ID="1" CUR_IND="1"
        DOC_HDLR_URL="${application.url}/krad/maintenance?methodToCall=docHandler&amp;dataObjectClassName=edu.sampleu.travel.dto.FiscalOfficerInfo"
        DOC_TYP_DESC="Create a New Fiscal Officer Maintenance Document"
        DOC_TYP_ID="3009"
        DOC_TYP_NM="FiscalOfficerInfoMaintenanceDocument"
        DOC_TYP_VER_NBR="0" GRP_ID="1"
        LBL="Fiscal Officer Info Maintenance Document"
        OBJ_ID="a4ecd35b-f35a-40ac-a9e1-ed47201281ec" PARNT_ID="2681"
        POST_PRCSR="org.kuali.rice.krad.workflow.postprocessor.KualiPostProcessor"
        RTE_VER_NBR="2" VER_NBR="1"/>
    <KREW_DOC_TYP_T ACTV_IND="1" CUR_IND="0"
        DOC_HDLR_URL="${kr.url}/maintenance.do?methodToCall=docHandler"
        DOC_TYP_ID="3010" DOC_TYP_NM="CampusMaintenanceDocument"
        DOC_TYP_VER_NBR="1"
        HELP_DEF_URL="http://site.kuali.org/rice/${rice.version}/reference/html/Help.html#campus"
        LBL="CampusMaintenanceDocument"
        OBJ_ID="88b31627-8d11-4115-9fbd-56c69d74abe6" PARNT_ID="2681"
        PREV_DOC_TYP_VER_NBR="2708" RTE_VER_NBR="2" VER_NBR="2"/>
    <KREW_DOC_TYP_T ACTV_IND="1" CUR_IND="0"
        DOC_HDLR_URL="${kr.url}/maintenance.do?methodToCall=docHandler"
        DOC_TYP_ID="3011" DOC_TYP_NM="CampusTypeMaintenanceDocument"
        DOC_TYP_VER_NBR="1"
        HELP_DEF_URL="http://site.kuali.org/rice/${rice.version}/reference/html/Help.html#campus_type"
        LBL="CampusTypeMaintenanceDocument"
        OBJ_ID="a8fae483-3099-4288-9f13-85e746c0369e" PARNT_ID="2681"
        PREV_DOC_TYP_VER_NBR="2709" RTE_VER_NBR="2" VER_NBR="2"/>
    <KREW_DOC_TYP_T ACTV_IND="1" BLNKT_APPR_GRP_ID="1" CUR_IND="0"
        DOC_HDLR_URL="${kr.url}/maintenance.do?methodToCall=docHandler"
        DOC_TYP_DESC="Create/edit a component" DOC_TYP_ID="3012"
        DOC_TYP_NM="ComponentMaintenanceDocument" DOC_TYP_VER_NBR="1"
        GRP_ID="1"
        HELP_DEF_URL="http://site.kuali.org/rice/${rice.version}/reference/html/Help.html#parameter_component"
        LBL="Component Maintenance Document"
        OBJ_ID="2dfa8e7d-66d7-436d-b664-3f85b62bd6cc" PARNT_ID="2681"
        POST_PRCSR="org.kuali.rice.krad.workflow.postprocessor.KualiPostProcessor"
        PREV_DOC_TYP_VER_NBR="3007" RTE_VER_NBR="2" VER_NBR="2"/>
    <KREW_DOC_TYP_T ACTV_IND="1" CUR_IND="0"
        DOC_HDLR_URL="${kr.url}/maintenance.do?methodToCall=docHandler"
        DOC_TYP_ID="3013" DOC_TYP_NM="CountryMaintenanceDocument"
        DOC_TYP_VER_NBR="1"
        HELP_DEF_URL="http://site.kuali.org/rice/${rice.version}/reference/html/Help.html#country"
        LBL="CountryMaintenanceDocument"
        OBJ_ID="589dc4de-1e6f-4381-9940-4dca71d3bb7f" PARNT_ID="2681"
        PREV_DOC_TYP_VER_NBR="2710" RTE_VER_NBR="2" VER_NBR="2"/>
    <KREW_DOC_TYP_T ACTV_IND="1" CUR_IND="0"
        DOC_HDLR_URL="${kr.url}/maintenance.do?methodToCall=docHandler"
        DOC_TYP_ID="3014" DOC_TYP_NM="CountyMaintenanceDocument"
        DOC_TYP_VER_NBR="1"
        HELP_DEF_URL="http://site.kuali.org/rice/${rice.version}/reference/html/Help.html#county"
        LBL="CountyMaintenanceDocument"
        OBJ_ID="bb4a6ba1-6bd2-489e-b3e8-0b367ce5524a" PARNT_ID="2681"
        PREV_DOC_TYP_VER_NBR="2711" RTE_VER_NBR="2" VER_NBR="2"/>
    <KREW_DOC_TYP_T ACTV_IND="1" BLNKT_APPR_GRP_ID="1" CUR_IND="0"
        DOC_HDLR_URL="${kr.url}/maintenance.do?methodToCall=docHandler"
        DOC_TYP_DESC="Workflow Maintenance Document Type Document"
        DOC_TYP_ID="3015" DOC_TYP_NM="DocumentTypeDocument"
        DOC_TYP_VER_NBR="1" GRP_ID="1"
        HELP_DEF_URL="http://site.kuali.org/rice/${rice.version}/reference/html/Help.html#document_type"
        LBL="Workflow Maintenance Document Type Document"
        OBJ_ID="ff36d34d-f1ed-440a-b937-9bda932e469f" PARNT_ID="2681"
        POST_PRCSR="org.kuali.rice.krad.workflow.postprocessor.KualiPostProcessor"
        PREV_DOC_TYP_VER_NBR="2011" RTE_VER_NBR="2" VER_NBR="2"/>
    <KREW_DOC_TYP_T ACTV_IND="1" BLNKT_APPR_GRP_ID="1" CUR_IND="0"
        DOC_HDLR_URL="${kr.url}/maintenance.do?methodToCall=docHandler"
        DOC_TYP_DESC="Create/edit parameter namespaces"
        DOC_TYP_ID="3016" DOC_TYP_NM="NamespaceMaintenanceDocument"
        DOC_TYP_VER_NBR="1" GRP_ID="1"
        HELP_DEF_URL="http://site.kuali.org/rice/${rice.version}/reference/html/Help.html#namespace"
        LBL="Namespace" OBJ_ID="88a66f90-713b-462e-a20b-18ba8b5fcb8a"
        PARNT_ID="2681"
        POST_PRCSR="org.kuali.rice.krad.workflow.postprocessor.KualiPostProcessor"
        PREV_DOC_TYP_VER_NBR="2031" RTE_VER_NBR="2" VER_NBR="2"/>
    <KREW_DOC_TYP_T ACTV_IND="1" BLNKT_APPR_GRP_ID="1" CUR_IND="0"
        DOC_HDLR_URL="${kr.url}/maintenance.do?methodToCall=docHandler"
        DOC_TYP_DESC="Create/edit a parameter detail type"
        DOC_TYP_ID="3017"
        DOC_TYP_NM="ParameterDetailTypeMaintenanceDocument"
        DOC_TYP_VER_NBR="1" GRP_ID="1"
        HELP_DEF_URL="http://site.kuali.org/rice/${rice.version}/reference/html/Help.html#parameter_component"
        LBL="Parameter Detail Type Maintenance Document"
        OBJ_ID="ec7058e7-60e3-4490-9454-4c200c8399b4" PARNT_ID="2681"
        POST_PRCSR="org.kuali.rice.krad.workflow.postprocessor.KualiPostProcessor"
        PREV_DOC_TYP_VER_NBR="2033" RTE_VER_NBR="2" VER_NBR="2"/>
    <KREW_DOC_TYP_T ACTV_IND="1" BLNKT_APPR_GRP_ID="1" CUR_IND="0"
        DOC_HDLR_URL="${kr.url}/maintenance.do?methodToCall=docHandler"
        DOC_TYP_DESC="Create/edit a parameter" DOC_TYP_ID="3018"
        DOC_TYP_NM="ParameterMaintenanceDocument" DOC_TYP_VER_NBR="1"
        GRP_ID="1"
        HELP_DEF_URL="http://site.kuali.org/rice/${rice.version}/reference/html/Help.html#parameter"
        LBL="Parameter Maintenance Document"
        OBJ_ID="71764534-da7d-4351-96e2-ff0cea75b011" PARNT_ID="2681"
        POST_PRCSR="org.kuali.rice.krad.workflow.postprocessor.KualiPostProcessor"
        PREV_DOC_TYP_VER_NBR="2034" RTE_VER_NBR="2" VER_NBR="2"/>
    <KREW_DOC_TYP_T ACTV_IND="1" BLNKT_APPR_GRP_ID="1" CUR_IND="0"
        DOC_HDLR_URL="${kr.url}/maintenance.do?methodToCall=docHandler"
        DOC_TYP_DESC="Create/edit a parameter type" DOC_TYP_ID="3019"
        DOC_TYP_NM="ParameterTypeMaintenanceDocument"
        DOC_TYP_VER_NBR="1" GRP_ID="1"
        HELP_DEF_URL="http://site.kuali.org/rice/${rice.version}/reference/html/Help.html#parameter_type"
        LBL="Parameter Type Maintenance Document"
        OBJ_ID="3def449d-e0b0-4f6c-84b2-427270a49685" PARNT_ID="2681"
        POST_PRCSR="org.kuali.rice.krad.workflow.postprocessor.KualiPostProcessor"
        PREV_DOC_TYP_VER_NBR="2032" RTE_VER_NBR="2" VER_NBR="2"/>
    <KREW_DOC_TYP_T ACTV_IND="1" CUR_IND="0"
        DOC_HDLR_URL="${kr.url}/maintenance.do?methodToCall=docHandler"
        DOC_TYP_ID="3020" DOC_TYP_NM="PostalCodeMaintenanceDocument"
        DOC_TYP_VER_NBR="1"
        HELP_DEF_URL="http://site.kuali.org/rice/${rice.version}/reference/html/Help.html#postal_code"
        LBL="PostalCodeMaintenanceDocument"
        OBJ_ID="ec358925-420e-4945-9291-b332d687bb4d" PARNT_ID="2681"
        PREV_DOC_TYP_VER_NBR="2712" RTE_VER_NBR="2" VER_NBR="2"/>
    <KREW_DOC_TYP_T ACTV_IND="1" CUR_IND="0"
        DOC_HDLR_URL="${kr.url}/maintenance.do?methodToCall=docHandler"
        DOC_TYP_ID="3021" DOC_TYP_NM="StateMaintenanceDocument"
        DOC_TYP_VER_NBR="1"
        HELP_DEF_URL="http://site.kuali.org/rice/${rice.version}/reference/html/Help.html#state"
        LBL="StateMaintenanceDocument"
        OBJ_ID="b6f3de8a-3e35-4803-ad34-4e2270a5c27c" PARNT_ID="2681"
        PREV_DOC_TYP_VER_NBR="2713" RTE_VER_NBR="2" VER_NBR="2"/>
    <KREW_DOC_TYP_T ACTV_IND="1" CUR_IND="0"
        DOC_HDLR_URL="${kr.url}/maintenance.do?methodToCall=docHandler"
        DOC_TYP_ID="3022"
        DOC_TYP_NM="IdentityManagementGenericPermissionMaintenanceDocument"
        DOC_TYP_VER_NBR="1"
        HELP_DEF_URL="http://site.kuali.org/rice/${rice.version}/reference/html/Help.html#permission"
        LBL="Permission" OBJ_ID="dbb321f2-e94b-46cb-8c1f-90ad7ee0ebe8"
        PARNT_ID="2994" PREV_DOC_TYP_VER_NBR="2999" RTE_VER_NBR="2" VER_NBR="2"/>
    <KREW_DOC_TYP_T ACTV_IND="1" CUR_IND="0"
        DOC_HDLR_URL="${kim.url}/identityManagementGroupDocument.do?methodToCall=docHandler"
        DOC_TYP_ID="3023" DOC_TYP_NM="IdentityManagementGroupDocument"
        DOC_TYP_VER_NBR="2"
        HELP_DEF_URL="http://site.kuali.org/rice/${rice.version}/reference/html/Help.html#group"
        LBL="Group" OBJ_ID="8248f839-af41-4d35-aff0-781c12ad920d"
        PARNT_ID="2994" PREV_DOC_TYP_VER_NBR="2996" RTE_VER_NBR="2" VER_NBR="2"/>
    <KREW_DOC_TYP_T ACTV_IND="1" CUR_IND="0"
        DOC_HDLR_URL="${kim.url}/identityManagementPersonDocument.do?methodToCall=docHandler"
        DOC_TYP_ID="3024" DOC_TYP_NM="IdentityManagementPersonDocument"
        DOC_TYP_VER_NBR="2"
        HELP_DEF_URL="http://site.kuali.org/rice/${rice.version}/reference/html/Help.html#person"
        LBL="Person" OBJ_ID="c9a8f243-b55a-407f-b8fc-0510f2d53c5e"
        PARNT_ID="2994" PREV_DOC_TYP_VER_NBR="2997" RTE_VER_NBR="2" VER_NBR="2"/>
    <KREW_DOC_TYP_T ACTV_IND="1" CUR_IND="0"
        DOC_HDLR_URL="${kr.url}/maintenance.do?methodToCall=docHandler"
        DOC_TYP_ID="3025"
        DOC_TYP_NM="IdentityManagementReviewResponsibilityMaintenanceDocument"
        DOC_TYP_VER_NBR="1"
        HELP_DEF_URL="http://site.kuali.org/rice/${rice.version}/reference/html/Help.html#responsibility"
        LBL="Review Responsibility"
        OBJ_ID="c1944296-8d8c-4995-ba0f-162853e9562c" PARNT_ID="2994"
        PREV_DOC_TYP_VER_NBR="2998" RTE_VER_NBR="2" VER_NBR="2"/>
    <KREW_DOC_TYP_T ACTV_IND="1" CUR_IND="0"
        DOC_HDLR_URL="${kim.url}/identityManagementRoleDocument.do?methodToCall=docHandler"
        DOC_TYP_ID="3026" DOC_TYP_NM="IdentityManagementRoleDocument"
        DOC_TYP_VER_NBR="2"
        HELP_DEF_URL="http://site.kuali.org/rice/${rice.version}/reference/html/Help.html#role"
        LBL="Role" OBJ_ID="4ee04b3f-c17c-4d5f-998e-192ae3692b72"
        PARNT_ID="2994" PREV_DOC_TYP_VER_NBR="2995" RTE_VER_NBR="2" VER_NBR="2"/>
    <KREW_DOC_TYP_T ACTV_IND="1" CUR_IND="0"
        DOC_HDLR_URL="${application.url}/kr-krad/maintenance?methodToCall=docHandler&amp;dataObjectClassName=org.kuali.rice.krad.demo.travel.dataobject.TravelAccountType"
        DOC_TYP_DESC="Create a Travel Account Type Maintenance Document"
        DOC_TYP_ID="3027"
        DOC_TYP_NM="TravelAccountTypeMaintenanceDocument"
        DOC_TYP_VER_NBR="0"
        LBL="Travel Account Type MaintenanceDocument"
        OBJ_ID="4f5f3a1b-f609-4da9-8dba-ed980b812ea1" PARNT_ID="2681"
        POST_PRCSR="org.kuali.rice.krad.workflow.postprocessor.KualiPostProcessor"
        RTE_VER_NBR="2" VER_NBR="2"/>
    <KREW_DOC_TYP_T ACTV_IND="1" BLNKT_APPR_GRP_ID="1" CUR_IND="0"
        DOC_HDLR_URL="${kr.krad.url}/maintenance?methodToCall=docHandler"
        DOC_TYP_DESC="Create a New Travel Attachment Group Sample Maintenance Document"
        DOC_TYP_ID="3028"
        DOC_TYP_NM="TravelAttachmentGroupSampleMaintenanceDocument"
        DOC_TYP_VER_NBR="0" GRP_ID="1"
        LBL="Travel Attachment Group Sample Maintenance Document"
        OBJ_ID="3cfc0612-c723-4a88-b3e8-084569b24c9c" PARNT_ID="2681"
        POST_PRCSR="org.kuali.rice.krad.workflow.postprocessor.KualiPostProcessor"
        RTE_VER_NBR="2" VER_NBR="2"/>
    <KREW_DOC_TYP_T ACTV_IND="1" BLNKT_APPR_GRP_ID="1" CUR_IND="0"
        DOC_HDLR_URL="${kr.krad.url}/maintenance?methodToCall=docHandler"
        DOC_TYP_DESC="Create a New Travel Attachment Sample Maintenance Document"
        DOC_TYP_ID="3029"
        DOC_TYP_NM="TravelAttachmentSampleMaintenanceDocument"
        DOC_TYP_VER_NBR="0" GRP_ID="1"
        LBL="Travel Attachment Sample Maintenance Document"
        OBJ_ID="23410ee8-f4c0-4368-884f-fef4899a2757" PARNT_ID="2681"
        POST_PRCSR="org.kuali.rice.krad.workflow.postprocessor.KualiPostProcessor"
        RTE_VER_NBR="2" VER_NBR="2"/>
    <KREW_DOC_TYP_T ACTV_IND="1" BLNKT_APPR_GRP_ID="1" CUR_IND="0"
        DOC_HDLR_URL="${application.url}/kr-krad/approval?methodToCall=docHandler"
        DOC_TYP_DESC="Create a New Travel Authorization Document"
        DOC_TYP_ID="3030" DOC_TYP_NM="TravelAuthorization"
        DOC_TYP_VER_NBR="1" GRP_ID="1"
        LBL="Travel Authorization Document"
        OBJ_ID="3c349396-3ce5-4929-a5ce-08b5677380d2" PARNT_ID="2681"
        POST_PRCSR="org.kuali.rice.krad.workflow.postprocessor.KualiPostProcessor"
        PREV_DOC_TYP_VER_NBR="3008" RTE_VER_NBR="2" VER_NBR="2"/>
    <KREW_DOC_TYP_T ACTV_IND="1" CUR_IND="0"
        DOC_TYP_DESC="Parent Document Type for all Travel Documents"
        DOC_TYP_ID="3031" DOC_TYP_NM="TravelDocument"
        DOC_TYP_VER_NBR="0" LBL="Travel Document"
        OBJ_ID="deb63983-c844-494d-b67f-2ae89b9c06f5" PARNT_ID="2681"
        RTE_VER_NBR="2" VER_NBR="12"/>
    <KREW_DOC_TYP_T ACTV_IND="1" CUR_IND="0"
        DOC_HDLR_URL="${application.url}/kr-krad/maintenance?methodToCall=docHandler&amp;dataObjectClassName=org.kuali.rice.krad.labs.LabsTravelCompany"
        DOC_TYP_DESC="Create a Labs Travel Company Maintenance Document"
        DOC_TYP_ID="3032"
        DOC_TYP_NM="LabsTravelCompanyMaintenanceDocument"
        DOC_TYP_VER_NBR="0"
        LBL="Labs Travel Company MaintenanceDocument"
        OBJ_ID="1c2f20f4-1f9e-4e0d-942f-bed83230ec7d" PARNT_ID="3067"
        POST_PRCSR="org.kuali.rice.krad.workflow.postprocessor.KualiPostProcessor"
        RTE_VER_NBR="2" VER_NBR="3"/>
    <KREW_DOC_TYP_T ACTV_IND="1" CUR_IND="0"
        DOC_HDLR_URL="${application.url}/kr-krad/maintenance?methodToCall=docHandler&amp;dataObjectClassName=edu.sampleu.travel.dataobject.TravelCompany"
        DOC_TYP_DESC="Create a Travel Company Maintenance Document"
        DOC_TYP_ID="3033" DOC_TYP_NM="TravelCompanyMaintenanceDocument"
        DOC_TYP_VER_NBR="0" LBL="Travel Company MaintenanceDocument"
        OBJ_ID="67a9db90-b3c5-4a04-8bfd-e76ffd02b309" PARNT_ID="3067"
        POST_PRCSR="org.kuali.rice.krad.workflow.postprocessor.KualiPostProcessor"
        RTE_VER_NBR="2" VER_NBR="3"/>
    <KREW_DOC_TYP_T ACTV_IND="1" CUR_IND="0"
        DOC_HDLR_URL="${application.url}/kr-krad/maintenance?methodToCall=docHandler&amp;dataObjectClassName=edu.sampleu.travel.dataobject.TravelDestination"
        DOC_TYP_DESC="Create a Travel Destination Maintenance Document"
        DOC_TYP_ID="3034"
        DOC_TYP_NM="TravelDestinationMaintenanceDocument"
        DOC_TYP_VER_NBR="0"
        LBL="Travel Travel Destination Maintenance Document"
        OBJ_ID="67f82c10-6aef-4bc3-b4f6-127a03744f88" PARNT_ID="3067"
        POST_PRCSR="org.kuali.rice.krad.workflow.postprocessor.KualiPostProcessor"
        RTE_VER_NBR="2" VER_NBR="3"/>
    <KREW_DOC_TYP_T ACTV_IND="1" CUR_IND="0"
        DOC_HDLR_URL="${application.url}/kr-krad/maintenance?methodToCall=docHandler&amp;dataObjectClassName=edu.sampleu.travel.dataobject.TravelMileageRate"
        DOC_TYP_DESC="Create a Travel Mileage Rate Maintenance Document"
        DOC_TYP_ID="3035"
        DOC_TYP_NM="TravelMileageRateMaintenanceDocument"
        DOC_TYP_VER_NBR="0"
        LBL="Travel Mileage Rate Maintenance Document"
        OBJ_ID="8b13064e-84ff-4731-a694-c17cb556e185" PARNT_ID="3067"
        POST_PRCSR="org.kuali.rice.krad.workflow.postprocessor.KualiPostProcessor"
        RTE_VER_NBR="2" VER_NBR="3"/>
    <KREW_DOC_TYP_T ACTV_IND="1" CUR_IND="0"
        DOC_HDLR_URL="${application.url}/kr-krad/maintenance?methodToCall=docHandler&amp;dataObjectClassName=edu.sampleu.travel.dataobject.TravelerDetail"
        DOC_TYP_DESC="Create a Traveler Detail Maintenance Document"
        DOC_TYP_ID="3036" DOC_TYP_NM="TravelerDetailMaintenanceDocument"
        DOC_TYP_VER_NBR="0"
        LBL="Travel Traveler Detail Maintenance Document"
        OBJ_ID="031a63e2-b29f-466d-8781-d19631740252" PARNT_ID="3067"
        POST_PRCSR="org.kuali.rice.krad.workflow.postprocessor.KualiPostProcessor"
        RTE_VER_NBR="2" VER_NBR="3"/>
    <KREW_DOC_TYP_T ACTV_IND="1" CUR_IND="0"
        DOC_HDLR_URL="${application.url}/kr-krad/maintenance?methodToCall=docHandler&amp;dataObjectClassName=edu.sampleu.travel.dataobject.TravelerType"
        DOC_TYP_DESC="Create a Traveler Type Maintenance Document"
        DOC_TYP_ID="3037" DOC_TYP_NM="TravelerTypeMaintenanceDocument"
        DOC_TYP_VER_NBR="0" LBL="Traveler Type Maintenance Document"
        OBJ_ID="004aae20-95cb-47b7-a644-5447d29dfec0" PARNT_ID="3067"
        POST_PRCSR="org.kuali.rice.krad.workflow.postprocessor.KualiPostProcessor"
        RTE_VER_NBR="2" VER_NBR="3"/>
    <KREW_DOC_TYP_T ACTV_IND="1" CUR_IND="0"
        DOC_HDLR_URL="${kr.url}/maintenance.do?methodToCall=docHandler"
        DOC_TYP_DESC="Create a Legacy KNS/OJB Travel Company Maintenance Document"
        DOC_TYP_ID="3038"
        DOC_TYP_NM="LegacyKnsTravelCompanyMaintenanceDocument"
        DOC_TYP_VER_NBR="0"
        LBL="Legacy KNS/OJB Travel Company MaintenanceDocument"
        OBJ_ID="0bdf6938-8b56-4dd8-8de7-34946b5224aa" PARNT_ID="3067"
        POST_PRCSR="org.kuali.rice.krad.workflow.postprocessor.KualiPostProcessor"
        RTE_VER_NBR="2" VER_NBR="3"/>
    <KREW_DOC_TYP_T ACTV_IND="1" CUR_IND="0"
        DOC_HDLR_URL="${application.url}/kr-krad/maintenance?methodToCall=docHandler&amp;dataObjectClassName=edu.sampleu.travel.dataobject.TravelCompany"
        DOC_TYP_DESC="Create a Legacy KRAD/JPA Travel Company Maintenance Document"
        DOC_TYP_ID="3039"
        DOC_TYP_NM="LegacyKradTravelCompanyMaintenanceDocument"
        DOC_TYP_VER_NBR="0"
        LBL="Legacy KRAD/JPA Travel Company MaintenanceDocument"
        OBJ_ID="672f1da3-b263-4905-82a9-056d31fe6d80" PARNT_ID="3067"
        POST_PRCSR="org.kuali.rice.krad.workflow.postprocessor.KualiPostProcessor"
        RTE_VER_NBR="2" VER_NBR="3"/>
    <KREW_DOC_TYP_T ACTV_IND="1" CUR_IND="0"
        DOC_HDLR_URL="${application.url}/legacyTravelAuthorization.do?methodToCall=docHandler"
        DOC_TYP_DESC="Travel Authorization Document in KNS and OJB"
        DOC_TYP_ID="3040" DOC_TYP_NM="LegacyTravelAuthorizationKns"
        DOC_TYP_VER_NBR="0" LBL="Travel Authorization"
        OBJ_ID="96a96606-7b55-4bcf-9868-65b157f6933e" PARNT_ID="2681"
        RTE_VER_NBR="2" VER_NBR="2"/>
    <KREW_DOC_TYP_T ACTV_IND="1" CUR_IND="0"
        DOC_HDLR_URL="${application.url}/kr-krad/maintenance?methodToCall=docHandler&amp;docTypeName=TravelAccountBulkUpdateMaintenanceDocument"
        DOC_TYP_DESC="Create a Travel Account Bulk Update Maintenance Document"
        DOC_TYP_ID="3041"
        DOC_TYP_NM="TravelAccountBulkUpdateMaintenanceDocument"
        DOC_TYP_VER_NBR="0"
        LBL="Travel Account Bulk Update MaintenanceDocument"
        OBJ_ID="03f86e49-8992-4a33-8e50-7f13dfab98bb" PARNT_ID="2681"
        POST_PRCSR="org.kuali.rice.krad.workflow.postprocessor.KualiPostProcessor"
        RTE_VER_NBR="2" VER_NBR="2"/>
    <KREW_DOC_TYP_T ACTV_IND="1" BLNKT_APPR_GRP_ID="1" CUR_IND="0"
        DOC_HDLR_URL="${kr.krad.url}/maintenance?methodToCall=docHandler"
        DOC_TYP_DESC="Create a New Travel Account Maintenance Document"
        DOC_TYP_ID="3042" DOC_TYP_NM="TravelAccountMaintenanceDocument"
        DOC_TYP_VER_NBR="2" GRP_ID="1"
        LBL="Travel Account Maintenance Document"
        OBJ_ID="a19a0b27-be0b-4528-91af-3737594851cd" PARNT_ID="3067"
        POST_PRCSR="org.kuali.rice.krad.workflow.postprocessor.KualiPostProcessor"
        PREV_DOC_TYP_VER_NBR="3006" RTE_VER_NBR="2" VER_NBR="3"/>
    <KREW_DOC_TYP_T ACTV_IND="1" CUR_IND="0"
        DOC_HDLR_URL="${application.url}/kr-krad/maintenance?methodToCall=docHandler&amp;dataObjectClassName=org.kuali.rice.krad.demo.travel.dataobject.TravelAccountType"
        DOC_TYP_DESC="Create a Travel Account Type Maintenance Document"
        DOC_TYP_ID="3043"
        DOC_TYP_NM="TravelAccountTypeMaintenanceDocument"
        DOC_TYP_VER_NBR="1"
        LBL="Travel Account Type MaintenanceDocument"
        OBJ_ID="59fd5b5c-c6e1-4415-83db-1a99a8ff8ebc" PARNT_ID="3031"
        POST_PRCSR="org.kuali.rice.krad.workflow.postprocessor.KualiPostProcessor"
        PREV_DOC_TYP_VER_NBR="3027" RTE_VER_NBR="2" VER_NBR="2"/>
    <KREW_DOC_TYP_T ACTV_IND="1" BLNKT_APPR_GRP_ID="1" CUR_IND="0"
        DOC_HDLR_URL="${application.url}/kr-krad/approval?methodToCall=docHandler"
        DOC_TYP_DESC="Create a New Travel Authorization Document"
        DOC_TYP_ID="3044" DOC_TYP_NM="TravelAuthorization"
        DOC_TYP_VER_NBR="2" GRP_ID="1"
        LBL="Travel Authorization Document"
        OBJ_ID="c5f01e5c-4198-4ab0-8c01-d2ccfa25fb83" PARNT_ID="3031"
        POST_PRCSR="org.kuali.rice.krad.workflow.postprocessor.KualiPostProcessor"
        PREV_DOC_TYP_VER_NBR="3030" RTE_VER_NBR="2" VER_NBR="2"/>
    <KREW_DOC_TYP_T ACTV_IND="1" CUR_IND="0"
        DOC_TYP_DESC="Labs Edl Maintenance Document" DOC_TYP_ID="3045"
        DOC_TYP_NM="LabsEdlMaintenanceDocument" DOC_TYP_VER_NBR="0"
        LBL="Labs Edl Maintenance Document"
        OBJ_ID="403ee5b8-e92b-4481-9559-3c01b8f6145a" PARNT_ID="2681"
        RTE_VER_NBR="2" VER_NBR="2"/>
    <KREW_DOC_TYP_T ACTV_IND="1" CUR_IND="1"
        DOC_HDLR_URL="${kr.url}/maintenance.do?methodToCall=docHandler"
        DOC_TYP_ID="3046" DOC_TYP_NM="CampusMaintenanceDocument"
        DOC_TYP_VER_NBR="2"
        HELP_DEF_URL="http://site.kuali.org/rice/${rice.version}/reference/html/Help.html#campus"
        LBL="CampusMaintenanceDocument"
        OBJ_ID="7c1bf1fc-203a-44e4-8a10-0a10673f431e" PARNT_ID="2681"
        PREV_DOC_TYP_VER_NBR="3010" RTE_VER_NBR="2" VER_NBR="1"/>
    <KREW_DOC_TYP_T ACTV_IND="1" CUR_IND="1"
        DOC_HDLR_URL="${kr.url}/maintenance.do?methodToCall=docHandler"
        DOC_TYP_ID="3047" DOC_TYP_NM="CampusTypeMaintenanceDocument"
        DOC_TYP_VER_NBR="2"
        HELP_DEF_URL="http://site.kuali.org/rice/${rice.version}/reference/html/Help.html#campus_type"
        LBL="CampusTypeMaintenanceDocument"
        OBJ_ID="e349461d-4321-4922-98eb-9226b4f958b5" PARNT_ID="2681"
        PREV_DOC_TYP_VER_NBR="3011" RTE_VER_NBR="2" VER_NBR="1"/>
    <KREW_DOC_TYP_T ACTV_IND="1" BLNKT_APPR_GRP_ID="1" CUR_IND="1"
        DOC_HDLR_URL="${kr.url}/maintenance.do?methodToCall=docHandler"
        DOC_TYP_DESC="Create/edit a component" DOC_TYP_ID="3048"
        DOC_TYP_NM="ComponentMaintenanceDocument" DOC_TYP_VER_NBR="2"
        GRP_ID="1"
        HELP_DEF_URL="http://site.kuali.org/rice/${rice.version}/reference/html/Help.html#parameter_component"
        LBL="Component Maintenance Document"
        OBJ_ID="b5d27e3b-8320-4821-9571-036600a1aeac" PARNT_ID="2681"
        POST_PRCSR="org.kuali.rice.krad.workflow.postprocessor.KualiPostProcessor"
        PREV_DOC_TYP_VER_NBR="3012" RTE_VER_NBR="2" VER_NBR="1"/>
    <KREW_DOC_TYP_T ACTV_IND="1" CUR_IND="1"
        DOC_HDLR_URL="${kr.url}/maintenance.do?methodToCall=docHandler"
        DOC_TYP_ID="3049" DOC_TYP_NM="CountryMaintenanceDocument"
        DOC_TYP_VER_NBR="2"
        HELP_DEF_URL="http://site.kuali.org/rice/${rice.version}/reference/html/Help.html#country"
        LBL="CountryMaintenanceDocument"
        OBJ_ID="7df3d42f-8528-4a87-9339-acfd82de49b1" PARNT_ID="2681"
        PREV_DOC_TYP_VER_NBR="3013" RTE_VER_NBR="2" VER_NBR="1"/>
    <KREW_DOC_TYP_T ACTV_IND="1" CUR_IND="1"
        DOC_HDLR_URL="${kr.url}/maintenance.do?methodToCall=docHandler"
        DOC_TYP_ID="3050" DOC_TYP_NM="CountyMaintenanceDocument"
        DOC_TYP_VER_NBR="2"
        HELP_DEF_URL="http://site.kuali.org/rice/${rice.version}/reference/html/Help.html#county"
        LBL="CountyMaintenanceDocument"
        OBJ_ID="27b33e12-961c-4fad-bf70-e18366fcf399" PARNT_ID="2681"
        PREV_DOC_TYP_VER_NBR="3014" RTE_VER_NBR="2" VER_NBR="1"/>
    <KREW_DOC_TYP_T ACTV_IND="1" BLNKT_APPR_GRP_ID="1" CUR_IND="1"
        DOC_HDLR_URL="${kr.url}/maintenance.do?methodToCall=docHandler"
        DOC_TYP_DESC="Workflow Maintenance Document Type Document"
        DOC_TYP_ID="3051" DOC_TYP_NM="DocumentTypeDocument"
        DOC_TYP_VER_NBR="2" GRP_ID="1"
        HELP_DEF_URL="http://site.kuali.org/rice/${rice.version}/reference/html/Help.html#document_type"
        LBL="Workflow Maintenance Document Type Document"
        OBJ_ID="f56a6fe4-92f3-4b73-876c-89cce8c3ee87" PARNT_ID="2681"
        POST_PRCSR="org.kuali.rice.krad.workflow.postprocessor.KualiPostProcessor"
        PREV_DOC_TYP_VER_NBR="3015" RTE_VER_NBR="2" VER_NBR="1"/>
    <KREW_DOC_TYP_T ACTV_IND="1" BLNKT_APPR_GRP_ID="1" CUR_IND="1"
        DOC_HDLR_URL="${kr.url}/maintenance.do?methodToCall=docHandler"
        DOC_TYP_DESC="Create/edit parameter namespaces"
        DOC_TYP_ID="3052" DOC_TYP_NM="NamespaceMaintenanceDocument"
        DOC_TYP_VER_NBR="2" GRP_ID="1"
        HELP_DEF_URL="http://site.kuali.org/rice/${rice.version}/reference/html/Help.html#namespace"
        LBL="Namespace" OBJ_ID="764dbf28-f6f2-4151-be48-8ea01e2dd728"
        PARNT_ID="2681"
        POST_PRCSR="org.kuali.rice.krad.workflow.postprocessor.KualiPostProcessor"
        PREV_DOC_TYP_VER_NBR="3016" RTE_VER_NBR="2" VER_NBR="1"/>
    <KREW_DOC_TYP_T ACTV_IND="1" BLNKT_APPR_GRP_ID="1" CUR_IND="1"
        DOC_HDLR_URL="${kr.url}/maintenance.do?methodToCall=docHandler"
        DOC_TYP_DESC="Create/edit a parameter detail type"
        DOC_TYP_ID="3053"
        DOC_TYP_NM="ParameterDetailTypeMaintenanceDocument"
        DOC_TYP_VER_NBR="2" GRP_ID="1"
        HELP_DEF_URL="http://site.kuali.org/rice/${rice.version}/reference/html/Help.html#parameter_component"
        LBL="Parameter Detail Type Maintenance Document"
        OBJ_ID="36438296-52e0-46bd-a392-18a7b0326dd1" PARNT_ID="2681"
        POST_PRCSR="org.kuali.rice.krad.workflow.postprocessor.KualiPostProcessor"
        PREV_DOC_TYP_VER_NBR="3017" RTE_VER_NBR="2" VER_NBR="1"/>
    <KREW_DOC_TYP_T ACTV_IND="1" BLNKT_APPR_GRP_ID="1" CUR_IND="1"
        DOC_HDLR_URL="${kr.url}/maintenance.do?methodToCall=docHandler"
        DOC_TYP_DESC="Create/edit a parameter" DOC_TYP_ID="3054"
        DOC_TYP_NM="ParameterMaintenanceDocument" DOC_TYP_VER_NBR="2"
        GRP_ID="1"
        HELP_DEF_URL="http://site.kuali.org/rice/${rice.version}/reference/html/Help.html#parameter"
        LBL="Parameter Maintenance Document"
        OBJ_ID="2d8caa8f-3021-42bf-8dbf-9811070465c7" PARNT_ID="2681"
        POST_PRCSR="org.kuali.rice.krad.workflow.postprocessor.KualiPostProcessor"
        PREV_DOC_TYP_VER_NBR="3018" RTE_VER_NBR="2" VER_NBR="1"/>
    <KREW_DOC_TYP_T ACTV_IND="1" BLNKT_APPR_GRP_ID="1" CUR_IND="1"
        DOC_HDLR_URL="${kr.url}/maintenance.do?methodToCall=docHandler"
        DOC_TYP_DESC="Create/edit a parameter type" DOC_TYP_ID="3055"
        DOC_TYP_NM="ParameterTypeMaintenanceDocument"
        DOC_TYP_VER_NBR="2" GRP_ID="1"
        HELP_DEF_URL="http://site.kuali.org/rice/${rice.version}/reference/html/Help.html#parameter_type"
        LBL="Parameter Type Maintenance Document"
        OBJ_ID="7ef8fcaa-5b05-4dfc-9919-b29fbda2efdd" PARNT_ID="2681"
        POST_PRCSR="org.kuali.rice.krad.workflow.postprocessor.KualiPostProcessor"
        PREV_DOC_TYP_VER_NBR="3019" RTE_VER_NBR="2" VER_NBR="1"/>
    <KREW_DOC_TYP_T ACTV_IND="1" CUR_IND="1"
        DOC_HDLR_URL="${kr.url}/maintenance.do?methodToCall=docHandler"
        DOC_TYP_ID="3056" DOC_TYP_NM="PostalCodeMaintenanceDocument"
        DOC_TYP_VER_NBR="2"
        HELP_DEF_URL="http://site.kuali.org/rice/${rice.version}/reference/html/Help.html#postal_code"
        LBL="PostalCodeMaintenanceDocument"
        OBJ_ID="28b3fb87-faa0-4216-8cd1-9ced44523949" PARNT_ID="2681"
        PREV_DOC_TYP_VER_NBR="3020" RTE_VER_NBR="2" VER_NBR="1"/>
    <KREW_DOC_TYP_T ACTV_IND="1" CUR_IND="1"
        DOC_HDLR_URL="${kr.url}/maintenance.do?methodToCall=docHandler"
        DOC_TYP_ID="3057" DOC_TYP_NM="StateMaintenanceDocument"
        DOC_TYP_VER_NBR="2"
        HELP_DEF_URL="http://site.kuali.org/rice/${rice.version}/reference/html/Help.html#state"
        LBL="StateMaintenanceDocument"
        OBJ_ID="0b3d9df7-e75a-47a3-8f9b-90c55630aa09" PARNT_ID="2681"
        PREV_DOC_TYP_VER_NBR="3021" RTE_VER_NBR="2" VER_NBR="1"/>
    <KREW_DOC_TYP_T ACTV_IND="1" CUR_IND="1"
        DOC_HDLR_URL="${kr.url}/maintenance.do?methodToCall=docHandler"
        DOC_TYP_ID="3058"
        DOC_TYP_NM="IdentityManagementGenericPermissionMaintenanceDocument"
        DOC_TYP_VER_NBR="2"
        HELP_DEF_URL="http://site.kuali.org/rice/${rice.version}/reference/html/Help.html#permission"
        LBL="Permission" OBJ_ID="0c791b5c-64fa-4003-b557-e33189b2ab72"
        PARNT_ID="2994" PREV_DOC_TYP_VER_NBR="3022" RTE_VER_NBR="2" VER_NBR="1"/>
    <KREW_DOC_TYP_T ACTV_IND="1" CUR_IND="1"
        DOC_HDLR_URL="${kim.url}/identityManagementGroupDocument.do?methodToCall=docHandler"
        DOC_TYP_ID="3059" DOC_TYP_NM="IdentityManagementGroupDocument"
        DOC_TYP_VER_NBR="3"
        HELP_DEF_URL="http://site.kuali.org/rice/${rice.version}/reference/html/Help.html#group"
        LBL="Group" OBJ_ID="45554235-4f2b-4a69-af4e-2e6e8110c0df"
        PARNT_ID="2994" PREV_DOC_TYP_VER_NBR="3023" RTE_VER_NBR="2" VER_NBR="1"/>
    <KREW_DOC_TYP_T ACTV_IND="1" CUR_IND="1"
        DOC_HDLR_URL="${kim.url}/identityManagementPersonDocument.do?methodToCall=docHandler"
        DOC_TYP_ID="3060" DOC_TYP_NM="IdentityManagementPersonDocument"
        DOC_TYP_VER_NBR="3"
        HELP_DEF_URL="http://site.kuali.org/rice/${rice.version}/reference/html/Help.html#person"
        LBL="Person" OBJ_ID="a0aa295f-abeb-4326-8200-30ae92406d3a"
        PARNT_ID="2994" PREV_DOC_TYP_VER_NBR="3024" RTE_VER_NBR="2" VER_NBR="1"/>
    <KREW_DOC_TYP_T ACTV_IND="1" CUR_IND="1"
        DOC_HDLR_URL="${kr.url}/maintenance.do?methodToCall=docHandler"
        DOC_TYP_ID="3061"
        DOC_TYP_NM="IdentityManagementReviewResponsibilityMaintenanceDocument"
        DOC_TYP_VER_NBR="2"
        HELP_DEF_URL="http://site.kuali.org/rice/${rice.version}/reference/html/Help.html#responsibility"
        LBL="Review Responsibility"
        OBJ_ID="08d1f823-3b4e-43eb-b912-77e5d447c0f6" PARNT_ID="2994"
        PREV_DOC_TYP_VER_NBR="3025" RTE_VER_NBR="2" VER_NBR="1"/>
    <KREW_DOC_TYP_T ACTV_IND="1" CUR_IND="1"
        DOC_HDLR_URL="${kim.url}/identityManagementRoleDocument.do?methodToCall=docHandler"
        DOC_TYP_ID="3062" DOC_TYP_NM="IdentityManagementRoleDocument"
        DOC_TYP_VER_NBR="3"
        HELP_DEF_URL="http://site.kuali.org/rice/${rice.version}/reference/html/Help.html#role"
        LBL="Role" OBJ_ID="8ac2a5de-8bf3-4b54-877e-3d3a34a87621"
        PARNT_ID="2994" PREV_DOC_TYP_VER_NBR="3026" RTE_VER_NBR="2" VER_NBR="1"/>
    <KREW_DOC_TYP_T ACTV_IND="1" CUR_IND="0"
        DOC_HDLR_URL="${application.url}/kr-krad/maintenance?methodToCall=docHandler&amp;dataObjectClassName=org.kuali.rice.krad.demo.travel.dataobject.TravelAccountType"
        DOC_TYP_DESC="Create a Travel Account Type Maintenance Document"
        DOC_TYP_ID="3063"
        DOC_TYP_NM="TravelAccountTypeMaintenanceDocument"
        DOC_TYP_VER_NBR="2"
        LBL="Travel Account Type MaintenanceDocument"
        OBJ_ID="3224de9d-52dc-4bd5-b13b-e32c8e3c9421" PARNT_ID="2681"
        POST_PRCSR="org.kuali.rice.krad.workflow.postprocessor.KualiPostProcessor"
        PREV_DOC_TYP_VER_NBR="3043" RTE_VER_NBR="2" VER_NBR="2"/>
    <KREW_DOC_TYP_T ACTV_IND="1" BLNKT_APPR_GRP_ID="1" CUR_IND="1"
        DOC_HDLR_URL="${kr.krad.url}/maintenance?methodToCall=docHandler"
        DOC_TYP_DESC="Create a New Travel Attachment Group Sample Maintenance Document"
        DOC_TYP_ID="3064"
        DOC_TYP_NM="TravelAttachmentGroupSampleMaintenanceDocument"
        DOC_TYP_VER_NBR="1" GRP_ID="1"
        LBL="Travel Attachment Group Sample Maintenance Document"
        OBJ_ID="fd166712-1e28-4743-b1af-d1d1dbffd8f2" PARNT_ID="2681"
        POST_PRCSR="org.kuali.rice.krad.workflow.postprocessor.KualiPostProcessor"
        PREV_DOC_TYP_VER_NBR="3028" RTE_VER_NBR="2" VER_NBR="1"/>
    <KREW_DOC_TYP_T ACTV_IND="1" BLNKT_APPR_GRP_ID="1" CUR_IND="1"
        DOC_HDLR_URL="${kr.krad.url}/maintenance?methodToCall=docHandler"
        DOC_TYP_DESC="Create a New Travel Attachment Sample Maintenance Document"
        DOC_TYP_ID="3065"
        DOC_TYP_NM="TravelAttachmentSampleMaintenanceDocument"
        DOC_TYP_VER_NBR="1" GRP_ID="1"
        LBL="Travel Attachment Sample Maintenance Document"
        OBJ_ID="2f706cba-0117-44a2-b9c3-f7c3ab5c16b8" PARNT_ID="2681"
        POST_PRCSR="org.kuali.rice.krad.workflow.postprocessor.KualiPostProcessor"
        PREV_DOC_TYP_VER_NBR="3029" RTE_VER_NBR="2" VER_NBR="1"/>
    <KREW_DOC_TYP_T ACTV_IND="1" BLNKT_APPR_GRP_ID="1" CUR_IND="0"
        DOC_HDLR_URL="${application.url}/kr-krad/approval?methodToCall=docHandler"
        DOC_TYP_DESC="Create a New Travel Authorization Document"
        DOC_TYP_ID="3066" DOC_TYP_NM="TravelAuthorization"
        DOC_TYP_VER_NBR="3" GRP_ID="1"
        LBL="Travel Authorization Document"
        OBJ_ID="b89b3ed5-ae52-4c3c-b8b5-9bdc52aa936c" PARNT_ID="2681"
        POST_PRCSR="org.kuali.rice.krad.workflow.postprocessor.KualiPostProcessor"
        PREV_DOC_TYP_VER_NBR="3044" RTE_VER_NBR="2" VER_NBR="2"/>
    <KREW_DOC_TYP_T ACTV_IND="1" CUR_IND="1"
        DOC_TYP_DESC="Parent Document Type for all Travel Documents"
        DOC_TYP_ID="3067" DOC_TYP_NM="TravelDocument"
        DOC_TYP_VER_NBR="1" LBL="Travel Document"
        OBJ_ID="e0dd2d71-8112-48e5-beff-21992f87a9f9" PARNT_ID="2681"
        PREV_DOC_TYP_VER_NBR="3031" RTE_VER_NBR="2" VER_NBR="10"/>
    <KREW_DOC_TYP_T ACTV_IND="1" CUR_IND="1"
        DOC_HDLR_URL="${application.url}/kr-krad/maintenance?methodToCall=docHandler&amp;dataObjectClassName=org.kuali.rice.krad.labs.LabsTravelCompany"
        DOC_TYP_DESC="Create a Labs Travel Company Maintenance Document"
        DOC_TYP_ID="3068"
        DOC_TYP_NM="LabsTravelCompanyMaintenanceDocument"
        DOC_TYP_VER_NBR="1"
        LBL="Labs Travel Company MaintenanceDocument"
        OBJ_ID="75a62eef-0041-4fc6-bad0-e5ef64fa98dc" PARNT_ID="3067"
        POST_PRCSR="org.kuali.rice.krad.workflow.postprocessor.KualiPostProcessor"
        PREV_DOC_TYP_VER_NBR="3032" RTE_VER_NBR="2" VER_NBR="1"/>
    <KREW_DOC_TYP_T ACTV_IND="1" CUR_IND="1"
        DOC_HDLR_URL="${application.url}/kr-krad/maintenance?methodToCall=docHandler&amp;dataObjectClassName=edu.sampleu.travel.dataobject.TravelCompany"
        DOC_TYP_DESC="Create a Travel Company Maintenance Document"
        DOC_TYP_ID="3069" DOC_TYP_NM="TravelCompanyMaintenanceDocument"
        DOC_TYP_VER_NBR="1" LBL="Travel Company MaintenanceDocument"
        OBJ_ID="d923c0f0-7504-4d39-9c02-13b2250e03b2" PARNT_ID="3067"
        POST_PRCSR="org.kuali.rice.krad.workflow.postprocessor.KualiPostProcessor"
        PREV_DOC_TYP_VER_NBR="3033" RTE_VER_NBR="2" VER_NBR="1"/>
    <KREW_DOC_TYP_T ACTV_IND="1" CUR_IND="1"
        DOC_HDLR_URL="${application.url}/kr-krad/maintenance?methodToCall=docHandler&amp;dataObjectClassName=edu.sampleu.travel.dataobject.TravelDestination"
        DOC_TYP_DESC="Create a Travel Destination Maintenance Document"
        DOC_TYP_ID="3070"
        DOC_TYP_NM="TravelDestinationMaintenanceDocument"
        DOC_TYP_VER_NBR="1"
        LBL="Travel Travel Destination Maintenance Document"
        OBJ_ID="e8a348cc-d7f0-427a-84d5-cfe48ddda739" PARNT_ID="3067"
        POST_PRCSR="org.kuali.rice.krad.workflow.postprocessor.KualiPostProcessor"
        PREV_DOC_TYP_VER_NBR="3034" RTE_VER_NBR="2" VER_NBR="1"/>
    <KREW_DOC_TYP_T ACTV_IND="1" CUR_IND="1"
        DOC_HDLR_URL="${application.url}/kr-krad/maintenance?methodToCall=docHandler&amp;dataObjectClassName=edu.sampleu.travel.dataobject.TravelMileageRate"
        DOC_TYP_DESC="Create a Travel Mileage Rate Maintenance Document"
        DOC_TYP_ID="3071"
        DOC_TYP_NM="TravelMileageRateMaintenanceDocument"
        DOC_TYP_VER_NBR="1"
        LBL="Travel Mileage Rate Maintenance Document"
        OBJ_ID="1718f680-f38d-470e-9c9e-f819ab0d25db" PARNT_ID="3067"
        POST_PRCSR="org.kuali.rice.krad.workflow.postprocessor.KualiPostProcessor"
        PREV_DOC_TYP_VER_NBR="3035" RTE_VER_NBR="2" VER_NBR="1"/>
    <KREW_DOC_TYP_T ACTV_IND="1" CUR_IND="1"
        DOC_HDLR_URL="${application.url}/kr-krad/maintenance?methodToCall=docHandler&amp;dataObjectClassName=edu.sampleu.travel.dataobject.TravelerDetail"
        DOC_TYP_DESC="Create a Traveler Detail Maintenance Document"
        DOC_TYP_ID="3072" DOC_TYP_NM="TravelerDetailMaintenanceDocument"
        DOC_TYP_VER_NBR="1"
        LBL="Travel Traveler Detail Maintenance Document"
        OBJ_ID="61eba92b-e617-4199-90d9-153fd3e6bbc6" PARNT_ID="3067"
        POST_PRCSR="org.kuali.rice.krad.workflow.postprocessor.KualiPostProcessor"
        PREV_DOC_TYP_VER_NBR="3036" RTE_VER_NBR="2" VER_NBR="1"/>
    <KREW_DOC_TYP_T ACTV_IND="1" CUR_IND="1"
        DOC_HDLR_URL="${application.url}/kr-krad/maintenance?methodToCall=docHandler&amp;dataObjectClassName=edu.sampleu.travel.dataobject.TravelerType"
        DOC_TYP_DESC="Create a Traveler Type Maintenance Document"
        DOC_TYP_ID="3073" DOC_TYP_NM="TravelerTypeMaintenanceDocument"
        DOC_TYP_VER_NBR="1" LBL="Traveler Type Maintenance Document"
        OBJ_ID="0260faea-474c-48bd-926d-2cbdf3b758b0" PARNT_ID="3067"
        POST_PRCSR="org.kuali.rice.krad.workflow.postprocessor.KualiPostProcessor"
        PREV_DOC_TYP_VER_NBR="3037" RTE_VER_NBR="2" VER_NBR="1"/>
    <KREW_DOC_TYP_T ACTV_IND="1" CUR_IND="1"
        DOC_HDLR_URL="${kr.url}/maintenance.do?methodToCall=docHandler"
        DOC_TYP_DESC="Create a Legacy KNS/OJB Travel Company Maintenance Document"
        DOC_TYP_ID="3074"
        DOC_TYP_NM="LegacyKnsTravelCompanyMaintenanceDocument"
        DOC_TYP_VER_NBR="1"
        LBL="Legacy KNS/OJB Travel Company MaintenanceDocument"
        OBJ_ID="2297f198-19f2-4e80-b3a5-15498f031a42" PARNT_ID="3067"
        POST_PRCSR="org.kuali.rice.krad.workflow.postprocessor.KualiPostProcessor"
        PREV_DOC_TYP_VER_NBR="3038" RTE_VER_NBR="2" VER_NBR="1"/>
    <KREW_DOC_TYP_T ACTV_IND="1" CUR_IND="1"
        DOC_HDLR_URL="${application.url}/kr-krad/maintenance?methodToCall=docHandler&amp;dataObjectClassName=edu.sampleu.travel.dataobject.TravelCompany"
        DOC_TYP_DESC="Create a Legacy KRAD/JPA Travel Company Maintenance Document"
        DOC_TYP_ID="3075"
        DOC_TYP_NM="LegacyKradTravelCompanyMaintenanceDocument"
        DOC_TYP_VER_NBR="1"
        LBL="Legacy KRAD/JPA Travel Company MaintenanceDocument"
        OBJ_ID="238f0f60-d894-4034-a482-62994443dc7c" PARNT_ID="3067"
        POST_PRCSR="org.kuali.rice.krad.workflow.postprocessor.KualiPostProcessor"
        PREV_DOC_TYP_VER_NBR="3039" RTE_VER_NBR="2" VER_NBR="1"/>
    <KREW_DOC_TYP_T ACTV_IND="1" CUR_IND="1"
        DOC_HDLR_URL="${application.url}/legacyTravelAuthorization.do?methodToCall=docHandler"
        DOC_TYP_DESC="Travel Authorization Document in KNS and OJB"
        DOC_TYP_ID="3076" DOC_TYP_NM="LegacyTravelAuthorizationKns"
        DOC_TYP_VER_NBR="1" LBL="Travel Authorization"
        OBJ_ID="b2d5caa9-7c4e-4d52-8f40-760bad48ab38" PARNT_ID="2681"
        PREV_DOC_TYP_VER_NBR="3040" RTE_VER_NBR="2" VER_NBR="1"/>
    <KREW_DOC_TYP_T ACTV_IND="1" CUR_IND="1"
        DOC_HDLR_URL="${application.url}/kr-krad/maintenance?methodToCall=docHandler&amp;docTypeName=TravelAccountBulkUpdateMaintenanceDocument"
        DOC_TYP_DESC="Create a Travel Account Bulk Update Maintenance Document"
        DOC_TYP_ID="3077"
        DOC_TYP_NM="TravelAccountBulkUpdateMaintenanceDocument"
        DOC_TYP_VER_NBR="1"
        LBL="Travel Account Bulk Update MaintenanceDocument"
        OBJ_ID="5261df33-df5e-42c4-b572-0a47e0918dd5" PARNT_ID="2681"
        POST_PRCSR="org.kuali.rice.krad.workflow.postprocessor.KualiPostProcessor"
        PREV_DOC_TYP_VER_NBR="3041" RTE_VER_NBR="2" VER_NBR="1"/>
    <KREW_DOC_TYP_T ACTV_IND="1" BLNKT_APPR_GRP_ID="1" CUR_IND="1"
        DOC_HDLR_URL="${kr.krad.url}/maintenance?methodToCall=docHandler"
        DOC_TYP_DESC="Create a New Travel Account Maintenance Document"
        DOC_TYP_ID="3078" DOC_TYP_NM="TravelAccountMaintenanceDocument"
        DOC_TYP_VER_NBR="3" GRP_ID="1"
        LBL="Travel Account Maintenance Document"
        OBJ_ID="a496787e-59f6-439f-a02d-db4a7e6f5ba9" PARNT_ID="3067"
        POST_PRCSR="org.kuali.rice.krad.workflow.postprocessor.KualiPostProcessor"
        PREV_DOC_TYP_VER_NBR="3042" RTE_VER_NBR="2" VER_NBR="1"/>
    <KREW_DOC_TYP_T ACTV_IND="1" CUR_IND="1"
        DOC_HDLR_URL="${application.url}/kr-krad/maintenance?methodToCall=docHandler&amp;dataObjectClassName=org.kuali.rice.krad.demo.travel.dataobject.TravelAccountType"
        DOC_TYP_DESC="Create a Travel Account Type Maintenance Document"
        DOC_TYP_ID="3079"
        DOC_TYP_NM="TravelAccountTypeMaintenanceDocument"
        DOC_TYP_VER_NBR="3"
        LBL="Travel Account Type MaintenanceDocument"
        OBJ_ID="11b7f951-f759-4816-a501-cd428aee3d85" PARNT_ID="3067"
        POST_PRCSR="org.kuali.rice.krad.workflow.postprocessor.KualiPostProcessor"
        PREV_DOC_TYP_VER_NBR="3063" RTE_VER_NBR="2" VER_NBR="1"/>
    <KREW_DOC_TYP_T ACTV_IND="1" BLNKT_APPR_GRP_ID="1" CUR_IND="1"
        DOC_HDLR_URL="${application.url}/kr-krad/approval?methodToCall=docHandler"
        DOC_TYP_DESC="Create a New Travel Authorization Document"
        DOC_TYP_ID="3080" DOC_TYP_NM="TravelAuthorization"
        DOC_TYP_VER_NBR="4" GRP_ID="1"
        LBL="Travel Authorization Document"
        OBJ_ID="4b2201db-79f5-4172-9265-e15fa3ee86d3" PARNT_ID="3067"
        POST_PRCSR="org.kuali.rice.krad.workflow.postprocessor.KualiPostProcessor"
        PREV_DOC_TYP_VER_NBR="3066" RTE_VER_NBR="2" VER_NBR="1"/>
    <KREW_DOC_TYP_T ACTV_IND="1" CUR_IND="1"
        DOC_TYP_DESC="Labs Edl Maintenance Document" DOC_TYP_ID="3081"
        DOC_TYP_NM="LabsEdlMaintenanceDocument" DOC_TYP_VER_NBR="1"
        LBL="Labs Edl Maintenance Document"
        OBJ_ID="95f395b1-b45d-47fc-9ad8-15ff6795864b" PARNT_ID="2681"
        PREV_DOC_TYP_VER_NBR="3045" RTE_VER_NBR="2" VER_NBR="1"/>
</dataset>
